MANIFEST.in
README.rst
setup.cfg
setup.py
collective/__init__.py
collective.langdet.egg-info/PKG-INFO
collective.langdet.egg-info/SOURCES.txt
collective.langdet.egg-info/dependency_links.txt
collective.langdet.egg-info/entry_points.txt
collective.langdet.egg-info/namespace_packages.txt
collective.langdet.egg-info/not-zip-safe
collective.langdet.egg-info/paster_plugins.txt
collective.langdet.egg-info/requires.txt
collective.langdet.egg-info/top_level.txt
collective/langdet/__init__.py
collective/langdet/configure.zcml
collective/langdet/interfaces.py
collective/langdet/tests.py
collective/langdet/utils.py
collective/langdet/profiles/default/metadata.xml
collective/langdet/scripts/set_language.py
docs/HISTORY.txt
docs/INSTALL.txt
docs/LICENSE.txt