Metadata-Version: 1.0
Name: collective.langdet
Version: 0.1
Summary: Language detection of content
Home-page: https://github.com/collective/collective.langdet
Author: Christian Ledermann
Author-email: christian.ledermann@gmail.com
License: GPL
Platform: UNKNOWN
Classifier: Framework :: Plone
Classifier: Framework :: Plone :: 4.0
Classifier: Framework :: Plone :: 4.1
Classifier: Programming Language :: Python
Classifier: Topic :: Text Processing :: Linguistic
Classifier: License :: OSI Approved :: GNU General Public License (GPL)
Classifier: Development Status :: 4 - Beta
Classifier: Environment :: Web Environment
